odoo8_addon_mgmtsystem_nonconformity-8.0.1.2.0.99.dev16-py2.7-nspkg.pth
odoo8_addon_mgmtsystem_nonconformity-8.0.1.2.0.99.dev16.dist-info/DESCRIPTION.rst
odoo8_addon_mgmtsystem_nonconformity-8.0.1.2.0.99.dev16.dist-info/METADATA
odoo8_addon_mgmtsystem_nonconformity-8.0.1.2.0.99.dev16.dist-info/RECORD
odoo8_addon_mgmtsystem_nonconformity-8.0.1.2.0.99.dev16.dist-info/WHEEL
odoo8_addon_mgmtsystem_nonconformity-8.0.1.2.0.99.dev16.dist-info/metadata.json
odoo8_addon_mgmtsystem_nonconformity-8.0.1.2.0.99.dev16.dist-info/namespace_packages.txt
odoo8_addon_mgmtsystem_nonconformity-8.0.1.2.0.99.dev16.dist-info/top_level.txt
odoo_addons/mgmtsystem_nonconformity/README.rst
odoo_addons/mgmtsystem_nonconformity/__init__.py
odoo_addons/mgmtsystem_nonconformity/__openerp__.py
odoo_addons/mgmtsystem_nonconformity/data/mail_message_subtype.xml
odoo_addons/mgmtsystem_nonconformity/data/mgmtsystem_nonconformity_cause.xml
odoo_addons/mgmtsystem_nonconformity/data/mgmtsystem_nonconformity_origin.xml
odoo_addons/mgmtsystem_nonconformity/data/mgmtsystem_nonconformity_severity.xml
odoo_addons/mgmtsystem_nonconformity/data/sequence.xml
odoo_addons/mgmtsystem_nonconformity/data/workflow.xml
odoo_addons/mgmtsystem_nonconformity/demo/mgmtsystem_nonconformity.xml
odoo_addons/mgmtsystem_nonconformity/demo/mgmtsystem_nonconformity_cause.xml
odoo_addons/mgmtsystem_nonconformity/demo/mgmtsystem_nonconformity_origin.xml
odoo_addons/mgmtsystem_nonconformity/i18n/de.po
odoo_addons/mgmtsystem_nonconformity/i18n/es.po
odoo_addons/mgmtsystem_nonconformity/i18n/fr.po
odoo_addons/mgmtsystem_nonconformity/i18n/hr.po
odoo_addons/mgmtsystem_nonconformity/i18n/id.po
odoo_addons/mgmtsystem_nonconformity/i18n/mgmtsystem_nonconformity.pot
odoo_addons/mgmtsystem_nonconformity/i18n/nb.po
odoo_addons/mgmtsystem_nonconformity/i18n/pt.po
odoo_addons/mgmtsystem_nonconformity/i18n/pt_BR.po
odoo_addons/mgmtsystem_nonconformity/i18n/sl.po
odoo_addons/mgmtsystem_nonconformity/i18n/sv.po
odoo_addons/mgmtsystem_nonconformity/i18n/tr.po
odoo_addons/mgmtsystem_nonconformity/i18n/vi.po
odoo_addons/mgmtsystem_nonconformity/migrations/7.0.1.0/openupgrade_analysis.txt
odoo_addons/mgmtsystem_nonconformity/migrations/7.0.1.0/post-migration.py
odoo_addons/mgmtsystem_nonconformity/models/__init__.py
odoo_addons/mgmtsystem_nonconformity/models/mgmtsystem_action.py
odoo_addons/mgmtsystem_nonconformity/models/mgmtsystem_nonconformity.py
odoo_addons/mgmtsystem_nonconformity/models/mgmtsystem_nonconformity_cause.py
